<constituencyResults><constituencyResult seqNo="514"><consituencyId>110</consituencyId><constituencyName>Burton</constituencyName><results><result><partyCode>LAB </partyCode><votes>18677</votes><share>42.10</share></result><result><partyCode>CON </partyCode><votes>16545</votes><share>37.30</share></result><result><partyCode>LD  </partyCode><votes>5538</votes><share>12.50</share></result><result><partyCode>OTH</partyCode><votes>2752</votes><share>6.20</share></result><result><partyCode>UKIP</partyCode><votes>856</votes><share>1.90</share></result></results></constituencyResult></constituencyResults>
