<constituencyResults><constituencyResult seqNo="208"><consituencyId>454</consituencyId><constituencyName>Pontypridd</constituencyName><results><result><partyCode>LAB </partyCode><votes>18534</votes><share>54.20</share></result><result><partyCode>LD  </partyCode><votes>6840</votes><share>20.00</share></result><result><partyCode>CON </partyCode><votes>3949</votes><share>11.60</share></result><result><partyCode>PC  </partyCode><votes>3757</votes><share>11.00</share></result><result><partyCode>UKIP</partyCode><votes>871</votes><share>2.50</share></result><result><partyCode>OTH</partyCode><votes>233</votes><share>0.70</share></result></results></constituencyResult></constituencyResults>
