<constituencyResults><constituencyResult seqNo="303"><consituencyId>260</consituencyId><constituencyName>Gedling</constituencyName><results><result><partyCode>LAB </partyCode><votes>20982</votes><share>46.60</share></result><result><partyCode>CON </partyCode><votes>16647</votes><share>37.00</share></result><result><partyCode>LD  </partyCode><votes>6169</votes><share>13.70</share></result><result><partyCode>UKIP</partyCode><votes>785</votes><share>1.70</share></result><result><partyCode>OTH</partyCode><votes>411</votes><share>0.90</share></result></results></constituencyResult></constituencyResults>
