<constituencyResults><constituencyResult seqNo="530"><consituencyId>490</consituencyId><constituencyName>St. Albans</constituencyName><results><result><partyCode>CON </partyCode><votes>16921</votes><share>37.30</share></result><result><partyCode>LAB </partyCode><votes>15587</votes><share>34.30</share></result><result><partyCode>LD  </partyCode><votes>11547</votes><share>25.40</share></result><result><partyCode>UKIP</partyCode><votes>706</votes><share>1.60</share></result><result><partyCode>OTH</partyCode><votes>649</votes><share>1.40</share></result></results></constituencyResult></constituencyResults>
