<constituencyResults><constituencyResult seqNo="565"><consituencyId>572</consituencyId><constituencyName>Tiverton &amp; Honiton</constituencyName><results><result><partyCode>CON </partyCode><votes>23961</votes><share>46.70</share></result><result><partyCode>LD  </partyCode><votes>14954</votes><share>29.10</share></result><result><partyCode>LAB </partyCode><votes>6851</votes><share>13.30</share></result><result><partyCode>UKIP</partyCode><votes>2466</votes><share>4.80</share></result><result><partyCode>OTH</partyCode><votes>1701</votes><share>3.30</share></result><result><partyCode>GRN </partyCode><votes>1399</votes><share>2.70</share></result></results></constituencyResult></constituencyResults>
