<constituencyResults><constituencyResult seqNo="96"><consituencyId>466</consituencyId><constituencyName>Redcar</constituencyName><results><result><partyCode>LAB </partyCode><votes>19968</votes><share>51.40</share></result><result><partyCode>LD  </partyCode><votes>7852</votes><share>20.20</share></result><result><partyCode>CON </partyCode><votes>6954</votes><share>17.90</share></result><result><partyCode>OTH</partyCode><votes>3523</votes><share>9.10</share></result><result><partyCode>UKIP</partyCode><votes>564</votes><share>1.50</share></result></results></constituencyResult></constituencyResults>
