<constituencyResults><constituencyResult seqNo="177"><consituencyId>457</consituencyId><constituencyName>Portsmouth North</constituencyName><results><result><partyCode>LAB </partyCode><votes>15858</votes><share>38.50</share></result><result><partyCode>CON </partyCode><votes>15543</votes><share>37.80</share></result><result><partyCode>LD  </partyCode><votes>8361</votes><share>20.30</share></result><result><partyCode>UKIP</partyCode><votes>1407</votes><share>3.40</share></result><result><partyCode>OTH</partyCode><votes>0</votes><share>0.00</share></result></results></constituencyResult></constituencyResults>
