<constituencyResults><constituencyResult seqNo="65"><consituencyId>530</consituencyId><constituencyName>Staffordshire South</constituencyName><results><result><partyCode>CON </partyCode><votes>13794</votes><share>50.60</share></result><result><partyCode>LAB </partyCode><votes>5448</votes><share>20.00</share></result><result><partyCode>LD  </partyCode><votes>3654</votes><share>13.40</share></result><result><partyCode>UKIP</partyCode><votes>2757</votes><share>10.10</share></result><result><partyCode>OTH</partyCode><votes>1144</votes><share>4.20</share></result><result><partyCode>GRN </partyCode><votes>437</votes><share>1.60</share></result></results></constituencyResult></constituencyResults>
