<constituencyResults><constituencyResult seqNo="311"><consituencyId>607</consituencyId><constituencyName>Weaver Vale</constituencyName><results><result><partyCode>LAB </partyCode><votes>17196</votes><share>45.70</share></result><result><partyCode>CON </partyCode><votes>11919</votes><share>31.70</share></result><result><partyCode>LD  </partyCode><votes>7435</votes><share>19.80</share></result><result><partyCode>UKIP</partyCode><votes>1072</votes><share>2.80</share></result><result><partyCode>OTH</partyCode><votes>0</votes><share>0.00</share></result></results></constituencyResult></constituencyResults>
