<constituencyResults><constituencyResult seqNo="646"><consituencyId>419</consituencyId><constituencyName>Newry &amp; Armagh</constituencyName><results><result><partyCode>SF  </partyCode><votes>20965</votes><share>41.40</share></result><result><partyCode>SDLP</partyCode><votes>12770</votes><share>25.20</share></result><result><partyCode>DUP </partyCode><votes>9311</votes><share>18.40</share></result><result><partyCode>UUP </partyCode><votes>7025</votes><share>13.90</share></result><result><partyCode>IND</partyCode><votes>625</votes><share>1.20</share></result><result><partyCode>OTH</partyCode><votes>0</votes><share>0.00</share></result></results></constituencyResult></constituencyResults>
