<constituencyResults><constituencyResult seqNo="24"><consituencyId>259</consituencyId><constituencyName>Gateshead</constituencyName><results><result><partyCode>LAB </partyCode><votes>21510</votes><share>61.40</share></result><result><partyCode>LD  </partyCode><votes>7265</votes><share>20.70</share></result><result><partyCode>CON </partyCode><votes>3564</votes><share>10.20</share></result><result><partyCode>OTH</partyCode><votes>1519</votes><share>4.30</share></result><result><partyCode>UKIP</partyCode><votes>1163</votes><share>3.30</share></result></results></constituencyResult></constituencyResults>
